{"Headline":{"EffectiveDate":"2021-04-05T14:00:00-04:00","EffectiveEpochDate":1617645600,"Severity":5,"Text":"Expect showers this afternoon","Category":"rain","EndDate":"2021-04-05T20:00:00-04:00","EndEpochDate":1617667200,"MobileLink":"http://m.accuweather.com/en/ca/toronto/m5h/extended-weather-forecast/55488?unit=c&lang=en-us","Link":"http://www.accuweather.com/en/ca/toronto/m5h/daily-weather-forecast/55488?unit=c&lang=en-us"},"DailyForecasts":[{"Date":"2021-04-05T07:00:00-04:00","EpochDate":1617620400,"Sun":{"Rise":"2021-04-05T06:53:00-04:00","EpochRise":1617619980,"Set":"2021-04-05T19:49:00-04:00","EpochSet":1617666540},"Moon":{"Rise":"2021-04-05T04:05:00-04:00","EpochRise":1617609900,"Set":"2021-04-05T13:04:00-04:00","EpochSet":1617642240,"Phase":"WaningCrescent","Age":23},"Temperature":{"Minimum":{"Value":3.3,"Unit":"C","UnitType":17},"Maximum":{"Value":11.1,"Unit":"C","UnitType":17}},"RealFeelTemperature":{"Minimum":{"Value":2.8,"Unit":"C","UnitType":17},"Maximum":{"Value":12.8,"Unit":"C","UnitType":17}},"RealFeelTemperatureShade":{"Minimum":{"Value":2.8,"Unit":"C","UnitType":17},"Maximum":{"Value":10.6,"Unit":"C","UnitType":17}},"HoursOfSun":3,"DegreeDaySummary":{"Heating":{"Value":11,"Unit":"C","UnitType":17},"Cooling":{"Value":0,"Unit":"C","UnitType":17}},"AirAndPollen":[{"Name":"AirQuality","Value":0,"Category":"Good","CategoryValue":1,"Type":"Ozone"},{"Name":"Grass","Value":0,"Category":"Low","CategoryValue":1},{"Name":"Mold","Value":0,"Category":"Low","CategoryValue":1},{"Name":"Tree","Value":0,"Category":"Low","CategoryValue":1},{"Name":"Ragweed","Value":0,"Category":"Low","CategoryValue":1},{"Name":"UVIndex","Value":4,"Category":"Moderate","CategoryValue":2}],"Day":{"Icon":13,"IconPhrase":"Mostly cloudy w/ showers","HasPrecipitation":true,"PrecipitationType":"Rain","PrecipitationIntensity":"Light","ShortPhrase":"A shower or two this afternoon","LongPhrase":"Some sun, then turning cloudy with a passing shower or two this afternoon","PrecipitationProbability":47,"ThunderstormProbability":20,"RainProbability":44,"SnowProbability":0,"IceProbability":0,"Wind":{"Speed":{"Value":9.7,"Unit":"km/h","UnitType":7},"Direction":{"Degrees":124,"Localized":"SE","English":"SE"}},"WindGust":{"Speed":{"Value":22.5,"Unit":"km/h","UnitType":7},"Direction":{"Degrees":124,"Localized":"SE","English":"SE"}},"TotalLiquid":{"Value":0.3,"Unit":"mm","UnitType":3},"Rain":{"Value":0.3,"Unit":"mm","UnitType":3},"Snow":{"Value":0,"Unit":"cm","UnitType":4},"Ice":{"Value":0,"Unit":"mm","UnitType":3},"HoursOfPrecipitation":0.5,"HoursOfRain":0.5,"HoursOfSnow":0,"HoursOfIce":0,"CloudCover":72},"Night":{"Icon":34,"IconPhrase":"Mostly clear","HasPrecipitation":false,"ShortPhrase":"Patchy clouds","LongPhrase":"Patchy clouds","PrecipitationProbability":0,"ThunderstormProbability":0,"RainProbability":0,"SnowProbability":0,"IceProbability":0,"Wind":{"Speed":{"Value":8,"Unit":"km/h","UnitType":7},"Direction":{"Degrees":359,"Localized":"N","English":"N"}},"WindGust":{"Speed":{"Value":11.3,"Unit":"km/h","UnitType":7},"Direction":{"Degrees":359,"Localized":"N","English":"N"}},"TotalLiquid":{"Value":0,"Unit":"mm","UnitType":3},"Rain":{"Value":0,"Unit":"mm","UnitType":3},"Snow":{"Value":0,"Unit":"cm","UnitType":4},"Ice":{"Value":0,"Unit":"mm","UnitType":3},"HoursOfPrecipitation":0,"HoursOfRain":0,"HoursOfSnow":0,"HoursOfIce":0,"CloudCover":22},"Sources":["AccuWeather"],"MobileLink":"http://m.accuweather.com/en/ca/toronto/m5h/daily-weather-forecast/55488?day=1&unit=c&lang=en-us","Link":"http://www.accuweather.com/en/ca/toronto/m5h/daily-weather-forecast/55488?day=1&unit=c&lang=en-us"},{"Date":"2021-04-06T07:00:00-04:00","EpochDate":1617706800,"Sun":{"Rise":"2021-04-06T06:51:00-04:00","EpochRise":1617706260,"Set":"2021-04-06T19:50:00-04:00","EpochSet":1617753000},"Moon":{"Rise":"2021-04-06T04:46:00-04:00","EpochRise":1617698760,"Set":"2021-04-06T14:12:00-04:00","EpochSet":1617732720,"Phase":"WaningCrescent","Age":24},"Temperature":{"Minimum":{"Value":3.3,"Unit":"C","UnitType":17},"Maximum":{"Value":8.9,"Unit":"C","UnitType":17}},"RealFeelTemperature":{"Minimum":{"Value":-1.1,"Unit":"C","UnitType":17},"Maximum":{"Value":9.4,"Unit":"C","UnitType":17}},"RealFeelTemperatureShade":{"Minimum":{"Value":-1.1,"Unit":"C","UnitType":17},"Maximum":{"Value":6.1,"Unit":"C","UnitType":17}},"HoursOfSun":1.5,"DegreeDaySummary":{"Heating":{"Value":12,"Unit":"C","UnitType":17},"Cooling":{"Value":0,"Unit":"C","UnitType":17}},"AirAndPollen":[{"Name":"AirQuality","Value":0,"Category":"Good","CategoryValue":1,"Type":"Ozone"},{"Name":"Grass","Value":0,"Category":"Low","CategoryValue":1},{"Name":"Mold","Value":0,"Category":"Low","CategoryValue":1},{"Name":"Tree","Value":0,"Category":"Low","CategoryValue":1},{"Name":"Ragweed","Value":0,"Category":"Low","CategoryValue":1},{"Name":"UVIndex","Value":4,"Category":"Moderate","CategoryValue":2}],"Day":{"Icon":12,"IconPhrase":"Showers","HasPrecipitation":true,"PrecipitationType":"Rain","PrecipitationIntensity":"Light","ShortPhrase":"An afternoon shower or two","LongPhrase":"Rather cloudy with a brief shower or two in the afternoon","PrecipitationProbability":65,"ThunderstormProbability":20,"RainProbability":65,"SnowProbability":0,"IceProbability":0,"Wind":{"Speed":{"Value":12.9,"Unit":"km/h","UnitType":7},"Direction":{"Degrees":95,"Localized":"E","English":"E"}},"WindGust":{"Speed":{"Value":19.3,"Unit":"km/h","UnitType":7},"Direction":{"Degrees":95,"Localized":"E","English":"E"}},"TotalLiquid":{"Value":2.5,"Unit":"mm","UnitType":3},"Rain":{"Value":2.5,"Unit":"mm","UnitType":3},"Snow":{"Value":0,"Unit":"cm","UnitType":4},"Ice":{"Value":0,"Unit":"mm","UnitType":3},"HoursOfPrecipitation":1,"HoursOfRain":1,"HoursOfSnow":0,"HoursOfIce":0,"CloudCover":86},"Night":{"Icon":12,"IconPhrase":"Showers","HasPrecipitation":true,"PrecipitationType":"Rain","PrecipitationIntensity":"Moderate","ShortPhrase":"A shower early; mostly cloudy","LongPhrase":"An evening shower; otherwise, mainly cloudy","PrecipitationProbability":58,"ThunderstormProbability":22,"RainProbability":58,"SnowProbability":0,"IceProbability":0,"Wind":{"Speed":{"Value":12.9,"Unit":"km/h","UnitType":7},"Direction":{"Degrees":61,"Localized":"ENE","English":"ENE"}},"WindGust":{"Speed":{"Value":19.3,"Unit":"km/h","UnitType":7},"Direction":{"Degrees":61,"Localized":"ENE","English":"ENE"}},"TotalLiquid":{"Value":1.5,"Unit":"mm","UnitType":3},"Rain":{"Value":1.5,"Unit":"mm","UnitType":3},"Snow":{"Value":0,"Unit":"cm","UnitType":4},"Ice":{"Value":0,"Unit":"mm","UnitType":3},"HoursOfPrecipitation":1,"HoursOfRain":1,"HoursOfSnow":0,"HoursOfIce":0,"CloudCover":86},"Sources":["AccuWeather"],"MobileLink":"http://m.accuweather.com/en/ca/toronto/m5h/daily-weather-forecast/55488?day=2&unit=c&lang=en-us","Link":"http://www.accuweather.com/en/ca/toronto/m5h/daily-weather-forecast/55488?day=2&unit=c&lang=en-us"},{"Date":"2021-04-07T07:00:00-04:00","EpochDate":1617793200,"Sun":{"Rise":"2021-04-07T06:49:00-04:00","EpochRise":1617792540,"Set":"2021-04-07T19:51:00-04:00","EpochSet":1617839460},"Moon":{"Rise":"2021-04-07T05:20:00-04:00","EpochRise":1617787200,"Set":"2021-04-07T15:20:00-04:00","EpochSet":1617823200,"Phase":"WaningCrescent","Age":25},"Temperature":{"Minimum":{"Value":6.1,"Unit":"C","UnitType":17},"Maximum":{"Value":9.4,"Unit":"C","UnitType":17}},"RealFeelTemperature":{"Minimum":{"Value":1.7,"Unit":"C","UnitType":17},"Maximum":{"Value":6.7,"Unit":"C","UnitType":17}},"RealFeelTemperatureShade":{"Minimum":{"Value":1.7,"Unit":"C","UnitType":17},"Maximum":{"Value":6.1,"Unit":"C","UnitType":17}},"HoursOfSun":1,"DegreeDaySummary":{"Heating":{"Value":10,"Unit":"C","UnitType":17},"Cooling":{"Value":0,"Unit":"C","UnitType":17}},"AirAndPollen":[{"Name":"AirQuality","Value":0,"Category":"Good","CategoryValue":1,"Type":"Ozone"},{"Name":"Grass","Value":0,"Category":"Low","CategoryValue":1},{"Name":"Mold","Value":100,"Category":"Low","CategoryValue":1},{"Name":"Tree","Value":0,"Category":"Low","CategoryValue":1},{"Name":"Ragweed","Value":0,"Category":"Low","CategoryValue":1},{"Name":"UVIndex","Value":6,"Category":"High","CategoryValue":3}],"Day":{"Icon":7,"IconPhrase":"Cloudy","HasPrecipitation":false,"ShortPhrase":"Overcast","LongPhrase":"Overcast","PrecipitationProbability":15,"ThunderstormProbability":5,"RainProbability":15,"SnowProbability":0,"IceProbability":0,"Wind":{"Speed":{"Value":16.1,"Unit":"km/h","UnitType":7},"Direction":{"Degrees":74,"Localized":"ENE","English":"ENE"}},"WindGust":{"Speed":{"Value":22.5,"Unit":"km/h","UnitType":7},"Direction":{"Degrees":74,"Localized":"ENE","English":"ENE"}},"TotalLiquid":{"Value":0,"Unit":"mm","UnitType":3},"Rain":{"Value":0,"Unit":"mm","UnitType":3},"Snow":{"Value":0,"Unit":"cm","UnitType":4},"Ice":{"Value":0,"Unit":"mm","UnitType":3},"HoursOfPrecipitation":0,"HoursOfRain":0,"HoursOfSnow":0,"HoursOfIce":0,"CloudCover":94},"Night":{"Icon":36,"IconPhrase":"Intermittent clouds","HasPrecipitation":false,"ShortPhrase":"Becoming clear","LongPhrase":"Becoming clear","PrecipitationProbability":21,"ThunderstormProbability":4,"RainProbability":21,"SnowProbability":0,"IceProbability":0,"Wind":{"Speed":{"Value":16.1,"Unit":"km/h","UnitType":7},"Direction":{"Degrees":75,"Localized":"ENE","English":"ENE"}},"WindGust":{"Speed":{"Value":22.5,"Unit":"km/h","UnitType":7},"Direction":{"Degrees":75,"Localized":"ENE","English":"ENE"}},"TotalLiquid":{"Value":0,"Unit":"mm","UnitType":3},"Rain":{"Value":0,"Unit":"mm","UnitType":3},"Snow":{"Value":0,"Unit":"cm","UnitType":4},"Ice":{"Value":0,"Unit":"mm","UnitType":3},"HoursOfPrecipitation":0,"HoursOfRain":0,"HoursOfSnow":0,"HoursOfIce":0,"CloudCover":46},"Sources":["AccuWeather"],"MobileLink":"http://m.accuweather.com/en/ca/toronto/m5h/daily-weather-forecast/55488?day=3&unit=c&lang=en-us","Link":"http://www.accuweather.com/en/ca/toronto/m5h/daily-weather-forecast/55488?day=3&unit=c&lang=en-us"},{"Date":"2021-04-08T07:00:00-04:00","EpochDate":1617879600,"Sun":{"Rise":"2021-04-08T06:47:00-04:00","EpochRise":1617878820,"Set":"2021-04-08T19:52:00-04:00","EpochSet":1617925920},"Moon":{"Rise":"2021-04-08T05:47:00-04:00","EpochRise":1617875220,"Set":"2021-04-08T16:26:00-04:00","EpochSet":1617913560,"Phase":"WaningCrescent","Age":26},"Temperature":{"Minimum":{"Value":8.3,"Unit":"C","UnitType":17},"Maximum":{"Value":13.2,"Unit":"C","UnitType":17}},"RealFeelTemperature":{"Minimum":{"Value":6.3,"Unit":"C","UnitType":17},"Maximum":{"Value":12.5,"Unit":"C","UnitType":17}},"RealFeelTemperatureShade":{"Minimum":{"Value":6.3,"Unit":"C","UnitType":17},"Maximum":{"Value":9.6,"Unit":"C","UnitType":17}},"HoursOfSun":10.1,"DegreeDaySummary":{"Heating":{"Value":7,"Unit":"C","UnitType":17},"Cooling":{"Value":0,"Unit":"C","UnitType":17}},"AirAndPollen":[{"Name":"AirQuality","Value":0,"Category":"Good","CategoryValue":1,"Type":"Ozone"},{"Name":"Grass","Value":0,"Category":"Low","CategoryValue":1},{"Name":"Mold","Value":135,"Category":"Low","CategoryValue":1},{"Name":"Ragweed","Value":0,"Category":"Low","CategoryValue":1},{"Name":"Tree","Value":0,"Category":"Low","CategoryValue":1},{"Name":"UVIndex","Value":6,"Category":"High","CategoryValue":3}],"Day":{"Icon":2,"IconPhrase":"Mostly sunny","HasPrecipitation":false,"ShortPhrase":"Sunny to partly cloudy","LongPhrase":"Sunny to partly cloudy","PrecipitationProbability":25,"ThunderstormProbability":1,"RainProbability":25,"SnowProbability":0,"IceProbability":0,"Wind":{"Speed":{"Value":20.4,"Unit":"km/h","UnitType":7},"Direction":{"Degrees":75,"Localized":"ENE","English":"ENE"}},"WindGust":{"Speed":{"Value":29.6,"Unit":"km/h","UnitType":7},"Direction":{"Degrees":76,"Localized":"ENE","English":"ENE"}},"TotalLiquid":{"Value":0,"Unit":"mm","UnitType":3},"Rain":{"Value":0,"Unit":"mm","UnitType":3},"Snow":{"Value":0,"Unit":"cm","UnitType":4},"Ice":{"Value":0,"Unit":"mm","UnitType":3},"HoursOfPrecipitation":0,"HoursOfRain":0,"HoursOfSnow":0,"HoursOfIce":0,"CloudCover":26},"Night":{"Icon":12,"IconPhrase":"Showers","HasPrecipitation":true,"PrecipitationType":"Rain","PrecipitationIntensity":"Light","ShortPhrase":"Cloudy with spotty showers","LongPhrase":"Cloudy with a couple of showers","PrecipitationProbability":63,"ThunderstormProbability":13,"RainProbability":63,"SnowProbability":0,"IceProbability":0,"Wind":{"Speed":{"Value":11.1,"Unit":"km/h","UnitType":7},"Direction":{"Degrees":124,"Localized":"SE","English":"SE"}},"WindGust":{"Speed":{"Value":18.5,"Unit":"km/h","UnitType":7},"Direction":{"Degrees":97,"Localized":"E","English":"E"}},"TotalLiquid":{"Value":3.4,"Unit":"mm","UnitType":3},"Rain":{"Value":3.4,"Unit":"mm","UnitType":3},"Snow":{"Value":0,"Unit":"cm","UnitType":4},"Ice":{"Value":0,"Unit":"mm","UnitType":3},"HoursOfPrecipitation":2,"HoursOfRain":2,"HoursOfSnow":0,"HoursOfIce":0,"CloudCover":92},"Sources":["AccuWeather"],"MobileLink":"http://m.accuweather.com/en/ca/toronto/m5h/daily-weather-forecast/55488?day=4&unit=c&lang=en-us","Link":"http://www.accuweather.com/en/ca/toronto/m5h/daily-weather-forecast/55488?day=4&unit=c&lang=en-us"},{"Date":"2021-04-09T07:00:00-04:00","EpochDate":1617966000,"Sun":{"Rise":"2021-04-09T06:45:00-04:00","EpochRise":1617965100,"Set":"2021-04-09T19:54:00-04:00","EpochSet":1618012440},"Moon":{"Rise":"2021-04-09T06:10:00-04:00","EpochRise":1617963000,"Set":"2021-04-09T17:31:00-04:00","EpochSet":1618003860,"Phase":"WaningCrescent","Age":27},"Temperature":{"Minimum":{"Value":6.4,"Unit":"C","UnitType":17},"Maximum":{"Value":12.4,"Unit":"C","UnitType":17}},"RealFeelTemperature":{"Minimum":{"Value":4.4,"Unit":"C","UnitType":17},"Maximum":{"Value":13.9,"Unit":"C","UnitType":17}},"RealFeelTemperatureShade":{"Minimum":{"Value":4.4,"Unit":"C","UnitType":17},"Maximum":{"Value":10.1,"Unit":"C","UnitType":17}},"HoursOfSun":7.8,"DegreeDaySummary":{"Heating":{"Value":9,"Unit":"C","UnitType":17},"Cooling":{"Value":0,"Unit":"C","UnitType":17}},"AirAndPollen":[{"Name":"AirQuality","Value":0,"Category":"Good","CategoryValue":1,"Type":"Ozone"},{"Name":"Grass","Value":0,"Category":"Low","CategoryValue":1},{"Name":"Mold","Value":203,"Category":"Low","CategoryValue":1},{"Name":"Ragweed","Value":0,"Category":"Low","CategoryValue":1},{"Name":"Tree","Value":0,"Category":"Low","CategoryValue":1},{"Name":"UVIndex","Value":6,"Category":"High","CategoryValue":3}],"Day":{"Icon":3,"IconPhrase":"Partly sunny","HasPrecipitation":true,"PrecipitationType":"Rain","PrecipitationIntensity":"Light","ShortPhrase":"A passing afternoon shower","LongPhrase":"Partly sunny with a passing shower in the afternoon","PrecipitationProbability":56,"ThunderstormProbability":11,"RainProbability":56,"SnowProbability":0,"IceProbability":0,"Wind":{"Speed":{"Value":13,"Unit":"km/h","UnitType":7},"Direction":{"Degrees":101,"Localized":"E","English":"E"}},"WindGust":{"Speed":{"Value":20.4,"Unit":"km/h","UnitType":7},"Direction":{"Degrees":95,"Localized":"E","English":"E"}},"TotalLiquid":{"Value":0.8,"Unit":"mm","UnitType":3},"Rain":{"Value":0.8,"Unit":"mm","UnitType":3},"Snow":{"Value":0,"Unit":"cm","UnitType":4},"Ice":{"Value":0,"Unit":"mm","UnitType":3},"HoursOfPrecipitation":0.5,"HoursOfRain":0.5,"HoursOfSnow":0,"HoursOfIce":0,"CloudCover":41},"Night":{"Icon":35,"IconPhrase":"Partly cloudy","HasPrecipitation":true,"PrecipitationType":"Rain","PrecipitationIntensity":"Moderate","ShortPhrase":"Partly cloudy, a shower late","LongPhrase":"Partly cloudy with a shower late","PrecipitationProbability":58,"ThunderstormProbability":12,"RainProbability":58,"SnowProbability":0,"IceProbability":0,"Wind":{"Speed":{"Value":9.3,"Unit":"km/h","UnitType":7},"Direction":{"Degrees":118,"Localized":"ESE","English":"ESE"}},"WindGust":{"Speed":{"Value":18.5,"Unit":"km/h","UnitType":7},"Direction":{"Degrees":111,"Localized":"ESE","English":"ESE"}},"TotalLiquid":{"Value":1.5,"Unit":"mm","UnitType":3},"Rain":{"Value":1.5,"Unit":"mm","UnitType":3},"Snow":{"Value":0,"Unit":"cm","UnitType":4},"Ice":{"Value":0,"Unit":"mm","UnitType":3},"HoursOfPrecipitation":1,"HoursOfRain":1,"HoursOfSnow":0,"HoursOfIce":0,"CloudCover":72},"Sources":["AccuWeather"],"MobileLink":"http://m.accuweather.com/en/ca/toronto/m5h/daily-weather-forecast/55488?day=5&unit=c&lang=en-us","Link":"http://www.accuweather.com/en/ca/toronto/m5h/daily-weather-forecast/55488?day=5&unit=c&lang=en-us"}],"lastUpdated":"2021-04-05T20:41:48.090Z"}